victor_project/__init__.py
victor_project/victor.py
Victor_project-0.1.4.dist-info/METADATA
Victor_project-0.1.4.dist-info/WHEEL
Victor_project-0.1.4.dist-info/top_level.txt
Victor_project-0.1.4.dist-info/RECORD
