Metadata-Version: 2.1
Name: Victor-project
Version: 0.1.4
Summary: First project
Home-page: UNKNOWN
Author: Munteanu-Victor
Author-email: munteanuviktor@gmail.com
License: UNKNOWN
Platform: UNKNOWN
